{
  "$schema": "https://mintlify.com/docs.json",
  "theme": "mint",
  "name": "Ezzy Bills",
  "colors": {
    "primary": "#ff0000"
  },
  "navigation": {
    "tabs": [
      {
        "tab": "API Reference",
        "groups": [
          {
            "group": "API Documentation",
            "pages": [ "api-reference/introduction" ]
          },
          {
            "group": "Endpoints",
            "openapi": {
              "source": "http://localhost:5000/swagger/v1/swagger.json",
              "directory": "api-reference"
            }
          }
        ]
      }
    ]
  }
}